tree_sitter_d2/__init__.py
tree_sitter_d2/__init__.pyi
tree_sitter_d2/_binding.abi3.so
tree_sitter_d2/binding.c
tree_sitter_d2/py.typed
tree_sitter_d2/queries/folds.scm
tree_sitter_d2/queries/highlights.scm
tree_sitter_d2/queries/injections.scm
tree_sitter_d2/queries/locals.scm
tree_sitter_d2-0.7.2.dist-info/METADATA
tree_sitter_d2-0.7.2.dist-info/WHEEL
tree_sitter_d2-0.7.2.dist-info/top_level.txt
tree_sitter_d2-0.7.2.dist-info/RECORD
tree_sitter_d2-0.7.2.dist-info/licenses/LICENSE
